Workbook

Sheet Sheet4
A3: Row Labels | B3: Sum of Revenue | G3: Row Labels | H3: Sum of Revenue | I3: Sum of Gross Profit | J3: gross margin
A4: Bangalore | B4: 8575000 | G4: Electronics | H4: 36069000 | I4: 10948200 | J4: =GETPIVOTDATA("Sum of Gross Profit",$G$3,"Category","Electronics")/GETPIVOTDATA("Sum of Revenue",$G$3,"Category","Electronics") -> 0.30353489 | M4: Row Labels | N4: Sum of Revenue | P4: Category | Q4: Gross Margin %
A5: Chennai | B5: 26733000 | G5: Furniture | H5: 6490000 | I5: 2596000 | J5: =GETPIVOTDATA("Sum of Gross Profit",$G$3,"Category","Furniture")/GETPIVOTDATA("Sum of Revenue",$G$3,"Category","Furniture") -> 0.4 | M5: Electronics | N5: 36069000 | P5: Electronics | Q5: 0.3035
A6: Hyderabad | B6: 7251000 | G6: Grand Total | H6: 42559000 | I6: 13544200 | J6: =GETPIVOTDATA("Sum of Gross Profit",$G$3)/GETPIVOTDATA("Sum of Revenue",$G$3) -> 0.31824526 | M6: Furniture | N6: 6490000 | P6: Furniture | Q6: 0.4
A7: Grand Total | B7: 42559000 | M7: Grand Total | N7: 42559000

Sheet dashboards
A1: Nova Retail Pvt. Ltd.
A2: Financial Performance Dashboard
A4: Total Revenue | C4: Total Gross Profit | E4: Gross Margin % | G4: Operating Expense | I4: Operating Profit | K4: Revenue Variance %
A5: ='financial analysis'!E6 -> 42559000 | C5: ='financial analysis'!E7 -> 13544200 | E5: ='financial analysis'!E8 -> 0.31824526 | G5: ='financial analysis'!E9 -> 4728500 | I5: ='financial analysis'!E10 -> 8815700 | K5: ='financial analysis'!E12 -> 0.049673203
A48: Management Insights
A49: 1.Total revenue reached ₹4.26 crore, exceeding the total budget by ₹20.14 lakh (4.97%).
A50: 2.Overall gross margin was 31.82%, while Furniture recorded a higher gross margin of 40.00% compared with Electronics at 30.35%.
A51: 3.Chennai generated the highest revenue at ₹2.67 crore, contributing approximately 62.8% of total revenue.
A52: 4.Electronics was the major revenue contributor at ₹3.61 crore, representing approximately 84.7% of total revenue.
A53: 5.Revenue increased from ₹22.00 lakh in January to ₹51.65 lakh in December, with December recording the highest monthly revenue.

Sheet Sheet2
A1: Result
A4: Insight | B4: What the data shows
A5: 1. Overall performance | B5: Total Revenue ₹4.26 crore; Actual Revenue Budget-ai ₹20.14 lakh (4.97%) exceed pannirukku.
A6: 2. Profitability | B6: Overall Gross Margin 31.82%. Furniture margin 40%, Electronics margin 30.35%.
A7: 3. City contribution | B7: Chennai revenue ₹2.67 crore, which is about 62.8% of total revenue. Bangalore ~20.1%, Hyderabad ~17.0%.
A8: 4. Category contribution | B8: Electronics ₹3.61 crore (~84.7%) revenue contribute pannudhu; Furniture ₹64.9 lakh (~15.3%).
A9: 5. Monthly trend | B9: Actual revenue Jan ₹22 lakh → Dec ₹51.65 lakh. December highest revenue month; January lowest.
A10: Meeting | B10: “The analysis shows that Electronics is the major revenue contributor, while Furniture generates a higher gross margin percentage. This highlights a difference between revenue contribution and profitability.”

Sheet tbl_FinancialData
A1: Date | B1: Month | C1: City | D1: Product | E1: Category | F1: Units Sold | G1: Revenue | H1: COGS | I1: Operating Expense | J1: Budget Revenue | K1: Budget Expense | L1: Gross Profit | M1: Gross Margin % | N1: Operating Profit | O1: Revenue Variance | P1: Revenue Variance %
A2: 46027 | B2: Jan | C2: Chennai | D2: Laptop | E2: Electronics | F2: 12 | G2: 720000 | H2: 540000 | I2: 85000 | J2: 700000 | K2: 80000 | L2: =tbl_FinancialData[[#This Row],[Revenue]]-tbl_FinancialData[[#This Row],[COGS]] -> 180000 | M2: =tbl_FinancialData[[#This Row],[Gross Profit]]/tbl_FinancialData[[#This Row],[Revenue]] -> 0.25 | N2: =tbl_FinancialData[[#This Row],[Gross Profit]]-tbl_FinancialData[[#This Row],[Operating Expense]] -> 95000 | O2: =tbl_FinancialData[[#This Row],[Revenue]]-tbl_FinancialData[[#This Row],[Budget Revenue]] -> 20000 | P2: =tbl_FinancialData[[#This Row],[Revenue Variance]]/tbl_FinancialData[[#This Row],[Budget Revenue]] -> 0.028571429
A3: 46030 | B3: Jan | C3: Bangalore | D3: Headphones | E3: Electronics | F3: 35 | G3: 105000 | H3: 63000 | I3: 18000 | J3: 110000 | K3: 20000 | L3: =tbl_FinancialData[[#This Row],[Revenue]]-tbl_FinancialData[[#This Row],[COGS]] -> 42000 | M3: =tbl_FinancialData[[#This Row],[Gross Profit]]/tbl_FinancialData[[#This Row],[Revenue]] -> 0.4 | N3: =tbl_FinancialData[[#This Row],[Gross Profit]]-tbl_FinancialData[[#This Row],[Operating Expense]] -> 24000 | O3: =tbl_FinancialData[[#This Row],[Revenue]]-tbl_FinancialData[[#This Row],[Budget Revenue]] -> -5000 | P3: =tbl_FinancialData[[#This Row],[Revenue Variance]]/tbl_FinancialData[[#This Row],[Budget Revenue]] -> -0.045454545
A4: 46037 | B4: Jan | C4: Hyderabad | D4: Office Chair | E4: Furniture | F4: 18 | G4: 90000 | H4: 54000 | I4: 12000 | J4: 85000 | K4: 10000 | L4: =tbl_FinancialData[[#This Row],[Revenue]]-tbl_FinancialData[[#This Row],[COGS]] -> 36000 | M4: =tbl_FinancialData[[#This Row],[Gross Profit]]/tbl_FinancialData[[#This Row],[Revenue]] -> 0.4 | N4: =tbl_FinancialData[[#This Row],[Gross Profit]]-tbl_FinancialData[[#This Row],[Operating Expense]] -> 24000 | O4: =tbl_FinancialData[[#This Row],[Revenue]]-tbl_FinancialData[[#This Row],[Budget Revenue]] -> 5000 | P4: =tbl_FinancialData[[#This Row],[Revenue Variance]]/tbl_FinancialData[[#This Row],[Budget Revenue]] -> 0.058823529
A5: 46043 | B5: Jan | C5: Chennai | D5: Monitor | E5: Electronics | F5: 20 | G5: 240000 | H5: 156000 | I5: 30000 | J5: 220000 | K5: 28000 | L5: =tbl_FinancialData[[#This Row],[Revenue]]-tbl_FinancialData[[#This Row],[COGS]] -> 84000 | M5: =tbl_FinancialData[[#This Row],[Gross Profit]]/tbl_FinancialData[[#This Row],[Revenue]] -> 0.35 | N5: =tbl_FinancialData[[#This Row],[Gross Profit]]-tbl_FinancialData[[#This Row],[Operating Expense]] -> 54000 | O5: =tbl_FinancialData[[#This Row],[Revenue]]-tbl_FinancialData[[#This Row],[Budget Revenue]] -> 20000 | P5: =tbl_FinancialData[[#This Row],[Revenue Variance]]/tbl_FinancialData[[#This Row],[Budget Revenue]] -> 0.090909091
A6: 46047 | B6: Jan | C6: Bangalore | D6: Desk | E6: Furniture | F6: 10 | G6: 100000 | H6: 60000 | I6: 15000 | J6: 95000 | K6: 14000 | L6: =tbl_FinancialData[[#This Row],[Revenue]]-tbl_FinancialData[[#This Row],[COGS]] -> 40000 | M6: =tbl_FinancialData[[#This Row],[Gross Profit]]/tbl_FinancialData[[#This Row],[Revenue]] -> 0.4 | N6: =tbl_FinancialData[[#This Row],[Gross Profit]]-tbl_FinancialData[[#This Row],[Operating Expense]] -> 25000 | O6: =tbl_FinancialData[[#This Row],[Revenue]]-tbl_FinancialData[[#This Row],[Budget Revenue]] -> 5000 | P6: =tbl_FinancialData[[#This Row],[Revenue Variance]]/tbl_FinancialData[[#This Row],[Budget Revenue]] -> 0.052631579
A7: 46050 | B7: Jan | C7: Hyderabad | D7: Keyboard | E7: Electronics | F7: 25 | G7: 75000 | H7: 37500 | I7: 10000 | J7: 80000 | K7: 9000 | L7: =tbl_FinancialData[[#This Row],[Revenue]]-tbl_FinancialData[[#This Row],[COGS]] -> 37500 | M7: =tbl_FinancialData[[#This Row],[Gross Profit]]/tbl_FinancialData[[#This Row],[Revenue]] -> 0.5 | N7: =tbl_FinancialData[[#This Row],[Gross Profit]]-tbl_FinancialData[[#This Row],[Operating Expense]] -> 27500 | O7: =tbl_FinancialData[[#This Row],[Revenue]]-tbl_FinancialData[[#This Row],[Budget Revenue]] -> -5000 | P7: =tbl_FinancialData[[#This Row],[Revenue Variance]]/tbl_FinancialData[[#This Row],[Budget Revenue]] -> -0.0625
A8: 46056 | B8: Feb | C8: Chennai | D8: Laptop | E8: Electronics | F8: 10 | G8: 600000 | H8: 450000 | I8: 75000 | J8: 580000 | K8: 70000 | L8: =tbl_FinancialData[[#This Row],[Revenue]]-tbl_FinancialData[[#This Row],[COGS]] -> 150000 | M8: =tbl_FinancialData[[#This Row],[Gross Profit]]/tbl_FinancialData[[#This Row],[Revenue]] -> 0.25 | N8: =tbl_FinancialData[[#This Row],[Gross Profit]]-tbl_FinancialData[[#This Row],[Operating Expense]] -> 75000 | O8: =tbl_FinancialData[[#This Row],[Revenue]]-tbl_FinancialData[[#This Row],[Budget Revenue]] -> 20000 | P8: =tbl_FinancialData[[#This Row],[Revenue Variance]]/tbl_FinancialData[[#This Row],[Budget Revenue]] -> 0.034482759
A9: 46060 | B9: Feb | C9: Bangalore | D9: Office Chair | E9: Furniture | F9: 22 | G9: 110000 | H9: 66000 | I9: 14000 | J9: 105000 | K9: 12000 | L9: =tbl_FinancialData[[#This Row],[Revenue]]-tbl_FinancialData[[#This Row],[COGS]] -> 44000 | M9: =tbl_FinancialData[[#This Row],[Gross Profit]]/tbl_FinancialData[[#This Row],[Revenue]] -> 0.4 | N9: =tbl_FinancialData[[#This Row],[Gross Profit]]-tbl_FinancialData[[#This Row],[Operating Expense]] -> 30000 | O9: =tbl_FinancialData[[#This Row],[Revenue]]-tbl_FinancialData[[#This Row],[Budget Revenue]] -> 5000 | P9: =tbl_FinancialData[[#This Row],[Revenue Variance]]/tbl_FinancialData[[#This Row],[Budget Revenue]] -> 0.047619048
A10: 46067 | B10: Feb | C10: Hyderabad | D10: Monitor | E10: Electronics | F10: 18 | G10: 216000 | H10: 140400 | I10: 26000 | J10: 210000 | K10: 25000 | L10: =tbl_FinancialData[[#This Row],[Revenue]]-tbl_FinancialData[[#This Row],[COGS]] -> 75600 | M10: =tbl_FinancialData[[#This Row],[Gross Profit]]/tbl_FinancialData[[#This Row],[Revenue]] -> 0.35 | N10: =tbl_FinancialData[[#This Row],[Gross Profit]]-tbl_FinancialData[[#This Row],[Operating Expense]] -> 49600 | O10: =tbl_FinancialData[[#This Row],[Revenue]]-tbl_FinancialData[[#This Row],[Budget Revenue]] -> 6000 | P10: =tbl_FinancialData[[#This Row],[Revenue Variance]]/tbl_FinancialData[[#This Row],[Budget Revenue]] -> 0.028571429
A11: 46075 | B11: Feb | C11: Chennai | D11: Desk | E11: Furniture | F11: 12 | G11: 120000 | H11: 72000 | I11: 16000 | J11: 115000 | K11: 15000 | L11: =tbl_FinancialData[[#This Row],[Revenue]]-tbl_FinancialData[[#This Row],[COGS]] -> 48000 | M11: =tbl_FinancialData[[#This Row],[Gross Profit]]/tbl_FinancialData[[#This Row],[Revenue]] -> 0.4 | N11: =tbl_FinancialData[[#This Row],[Gross Profit]]-tbl_FinancialData[[#This Row],[Operating Expense]] -> 32000 | O11: =tbl_FinancialData[[#This Row],[Revenue]]-tbl_FinancialData[[#This Row],[Budget Revenue]] -> 5000 | P11: =tbl_FinancialData[[#This Row],[Revenue Variance]]/tbl_FinancialData[[#This Row],[Budget Revenue]] -> 0.043478261
A12: 46079 | B12: Feb | C12: Bangalore | D12: Keyboard | E12: Electronics | F12: 30 | G12: 90000 | H12: 45000 | I12: 11000 | J12: 85000 | K12: 10000 | L12: =tbl_FinancialData[[#This Row],[Revenue]]-tbl_FinancialData[[#This Row],[COGS]] -> 45000 | M12: =tbl_FinancialData[[#This Row],[Gross Profit]]/tbl_FinancialData[[#This Row],[Revenue]] -> 0.5 | N12: =tbl_FinancialData[[#This Row],[Gross Profit]]-tbl_FinancialData[[#This Row],[Operating Expense]] -> 34000 | O12: =tbl_FinancialData[[#This Row],[Revenue]]-tbl_FinancialData[[#This Row],[Budget Revenue]] -> 5000 | P12: =tbl_FinancialData[[#This Row],[Revenue Variance]]/tbl_FinancialData[[#This Row],[Budget Revenue]] -> 0.058823529
A13: 46084 | B13: Mar | C13: Chennai | D13: Laptop | E13: Electronics | F13: 14 | G13: 840000 | H13: 630000 | I13: 90000 | J13: 800000 | K13: 85000 | L13: =tbl_FinancialData[[#This Row],[Revenue]]-tbl_FinancialData[[#This Row],[COGS]] -> 210000 | M13: =tbl_FinancialData[[#This Row],[Gross Profit]]/tbl_FinancialData[[#This Row],[Revenue]] -> 0.25 | N13: =tbl_FinancialData[[#This Row],[Gross Profit]]-tbl_FinancialData[[#This Row],[Operating Expense]] -> 120000 | O13: =tbl_FinancialData[[#This Row],[Revenue]]-tbl_FinancialData[[#This Row],[Budget Revenue]] -> 40000 | P13: =tbl_FinancialData[[#This Row],[Revenue Variance]]/tbl_FinancialData[[#This Row],[Budget Revenue]] -> 0.05
... A132: 46383 | B132: Dec | C132: Bangalore | D132: Headphones | E132: Electronics | F132: 72 | G132: 216000 | H132: 129600 | I132: 36000 | J132: 205000 | K132: 34000 | L132: =tbl_FinancialData[[#This Row],[Revenue]]-tbl_FinancialData[[#This Row],[COGS]] -> 86400 | M132: =tbl_FinancialData[[#This Row],[Gross Profit]]/tbl_FinancialData[[#This Row],[Revenue]] -> 0.4 | N132: =tbl_FinancialData[[#This Row],[Gross Profit]]-tbl_FinancialData[[#This Row],[Operating Expense]] -> 50400 | O132: =tbl_FinancialData[[#This Row],[Revenue]]-tbl_FinancialData[[#This Row],[Budget Revenue]] -> 11000 | P132: =tbl_FinancialData[[#This Row],[Revenue Variance]]/tbl_FinancialData[[#This Row],[Budget Revenue]] -> 0.053658537

Sheet financial analysis
A1: Nova Retail Pvt. Ltd.
A2: Financial Performance Analysis
A5: Key Financial Metrics | E5: Value
A6: Total Revenue | E6: 42559000
A7: Total Gross Profit | E7: 13544200
A8: Gross Margin % | E8: 0.31824526
A9: Total Operating Expense | E9: 4728500
A10: Total Operating Profit | E10: 8815700
A11: Revenue Variance | E11: 2014000
A12: Revenue Variance % | E12: 0.049673203
A14: A | B14: B | C14: C | D14: D | E14: E | F14: F
A15: Month | B15: Actual Revenue | C15: Budget Revenue | D15: Revenue Variance | E15: Revenue Variance % | F15: Operating profit
A16: Jan | B16: =SUMIFS(tbl_FinancialData[Revenue],tbl_FinancialData[Month],A16) -> 2200000 | C16: =SUMIFS(tbl_FinancialData[Budget Revenue],tbl_FinancialData[Month],A16) -> 2132000 | D16: =B16-C16 -> 68000 | E16: =D16/C16 -> 0.031894934 | F16: =SUMIFS(tbl_FinancialData[Operating Profit],tbl_FinancialData[Month],A16) -> 410900
A17: Feb | B17: =SUMIFS(tbl_FinancialData[Revenue],tbl_FinancialData[Month],A17) -> 2128000 | C17: =SUMIFS(tbl_FinancialData[Budget Revenue],tbl_FinancialData[Month],A17) -> 2047000 | D17: =B17-C17 -> 81000 | E17: =D17/C17 -> 0.039570103 | F17: =SUMIFS(tbl_FinancialData[Operating Profit],tbl_FinancialData[Month],A17) -> 412500
A18: Mar | B18: =SUMIFS(tbl_FinancialData[Revenue],tbl_FinancialData[Month],A18) -> 2701000 | C18: =SUMIFS(tbl_FinancialData[Budget Revenue],tbl_FinancialData[Month],A18) -> 2581000 | D18: =B18-C18 -> 120000 | E18: =D18/C18 -> 0.046493607 | F18: =SUMIFS(tbl_FinancialData[Operating Profit],tbl_FinancialData[Month],A18) -> 527800
A19: Apr | B19: =SUMIFS(tbl_FinancialData[Revenue],tbl_FinancialData[Month],A19) -> 2802000 | C19: =SUMIFS(tbl_FinancialData[Budget Revenue],tbl_FinancialData[Month],A19) -> 2698000 | D19: =B19-C19 -> 104000 | E19: =D19/C19 -> 0.038547072 | F19: =SUMIFS(tbl_FinancialData[Operating Profit],tbl_FinancialData[Month],A19) -> 578000
A20: May | B20: =SUMIFS(tbl_FinancialData[Revenue],tbl_FinancialData[Month],A20) -> 3035000 | C20: =SUMIFS(tbl_FinancialData[Budget Revenue],tbl_FinancialData[Month],A20) -> 2899000 | D20: =B20-C20 -> 136000 | E20: =D20/C20 -> 0.046912729 | F20: =SUMIFS(tbl_FinancialData[Operating Profit],tbl_FinancialData[Month],A20) -> 615900
A21: Jun | B21: =SUMIFS(tbl_FinancialData[Revenue],tbl_FinancialData[Month],A21) -> 3461000 | C21: =SUMIFS(tbl_FinancialData[Budget Revenue],tbl_FinancialData[Month],A21) -> 3273000 | D21: =B21-C21 -> 188000 | E21: =D21/C21 -> 0.057439658 | F21: =SUMIFS(tbl_FinancialData[Operating Profit],tbl_FinancialData[Month],A21) -> 715300
A22: Jul | B22: =SUMIFS(tbl_FinancialData[Revenue],tbl_FinancialData[Month],A22) -> 3730000 | C22: =SUMIFS(tbl_FinancialData[Budget Revenue],tbl_FinancialData[Month],A22) -> 3557000 | D22: =B22-C22 -> 173000 | E22: =D22/C22 -> 0.048636491 | F22: =SUMIFS(tbl_FinancialData[Operating Profit],tbl_FinancialData[Month],A22) -> 780900
A23: Aug | B23: =SUMIFS(tbl_FinancialData[Revenue],tbl_FinancialData[Month],A23) -> 4125000 | C23: =SUMIFS(tbl_FinancialData[Budget Revenue],tbl_FinancialData[Month],A23) -> 3906000 | D23: =B23-C23 -> 219000 | E23: =D23/C23 -> 0.056067588 | F23: =SUMIFS(tbl_FinancialData[Operating Profit],tbl_FinancialData[Month],A23) -> 869900
A24: Sep | B24: =SUMIFS(tbl_FinancialData[Revenue],tbl_FinancialData[Month],A24) -> 3956000 | C24: =SUMIFS(tbl_FinancialData[Budget Revenue],tbl_FinancialData[Month],A24) -> 3770000 | D24: =B24-C24 -> 186000 | E24: =D24/C24 -> 0.04933687 | F24: =SUMIFS(tbl_FinancialData[Operating Profit],tbl_FinancialData[Month],A24) -> 832500
A25: Oct | B25: =SUMIFS(tbl_FinancialData[Revenue],tbl_FinancialData[Month],A25) -> 4501000 | C25: =SUMIFS(tbl_FinancialData[Budget Revenue],tbl_FinancialData[Month],A25) -> 4261000 | D25: =B25-C25 -> 240000 | E25: =D25/C25 -> 0.056324806 | F25: =SUMIFS(tbl_FinancialData[Operating Profit],tbl_FinancialData[Month],A25) -> 956700
A26: Nov | B26: =SUMIFS(tbl_FinancialData[Revenue],tbl_FinancialData[Month],A26) -> 4755000 | C26: =SUMIFS(tbl_FinancialData[Budget Revenue],tbl_FinancialData[Month],A26) -> 4523000 | D26: =B26-C26 -> 232000 | E26: =D26/C26 -> 0.051293389 | F26: =SUMIFS(tbl_FinancialData[Operating Profit],tbl_FinancialData[Month],A26) -> 1013400
A27: Dec | B27: =SUMIFS(tbl_FinancialData[Revenue],tbl_FinancialData[Month],A27) -> 5165000 | C27: =SUMIFS(tbl_FinancialData[Budget Revenue],tbl_FinancialData[Month],A27) -> 4898000 | D27: =B27-C27 -> 267000 | E27: =D27/C27 -> 0.054512046 | F27: =SUMIFS(tbl_FinancialData[Operating Profit],tbl_FinancialData[Month],A27) -> 1101900
A29: Row Labels | B29: Sum of Revenue
A30: Bangalore | B30: 8575000
A31: Chennai | B31: 26733000
A32: Hyderabad | B32: 7251000
A33: Grand Total | B33: 42559000
